{
  "category": "City",
  "sourceSpelling": "Макіївка",
  "correctSpelling": "Makiivka",
  "incorrectSpellings": [
    "Makiyivka",
    "Makeyevka",
    "Makeievka"
  ],
  "relatedSpellings": [
    "Макеевка",
    "Дмитріївськ",
    "Дмитриевск",
    "Dmytriivsk",
    "Dmitrievsk",
    "Дмитріївськ-Сталінськ",
    "Дмитриевск-Сталинск",
    "Dmitrievsk-Stalinsk"
  ],
  "description": "Renamed from \"Dmytriivsk\" in 2015.",
  "links": [
    {
      "name": "Wikipedia: Makiivka",
      "url": "https://en.wikipedia.org/wiki/Makiivka"
    }
  ],
  "location": {
    "lat": 48.0556,
    "lng": 37.9611
  }
}