{
  "category": "Geography",
  "name": "Дніпро",
  "translation": "Dnipro",
  "mistranslations": [
    "Dnepr",
    "Dnieper",
    "Dniepr",
    "Dniepropetrovsk",
    "Dnepropetrovsk",
    "Dnipropetrovsk"
  ],
  "aliases": [
    "Днепр",
    "Днепропетровск"
  ],
  "description": "The city shares the same name as the river Dnipro that it was founded on.",
  "location": {
    "latitude": 48.45,
    "longitude": 34.9833
  },
  "externalLinks": [
    {
      "name": "Wikipedia: Dnipro",
      "url": "https://en.wikipedia.org/wiki/Dnipro"
    }
  ]
}